tfan/__init__.py
tfan/_version.py
tfan/core/__init__.py
tfan/core/models.py
thermal_face_alignment-1.0.0a4.dist-info/licenses/LICENSE.txt
thermal_face_alignment-1.0.0a4.dist-info/METADATA
thermal_face_alignment-1.0.0a4.dist-info/WHEEL
thermal_face_alignment-1.0.0a4.dist-info/top_level.txt
thermal_face_alignment-1.0.0a4.dist-info/RECORD
