Metadata-Version: 2.4
Name: thermal-face-alignment
Version: 1.0.0a4
Summary:  implementation and weights for facial landmarks in thermal images trained with the dataset described in 'T-FAKE: Synthesizing Thermal Images for Facial Landmarking'.
Author-email: Philipp Flotho <Philipp.Flotho@uni-saarland.de>, Moritz Piening <piening@math.tu-berlin.de>
License: CC BY-NC-SA 4.0
Classifier: Development Status :: 3 - Alpha
Classifier: Intended Audience :: Science/Research
Classifier: License :: Other/Proprietary License
Classifier: Operating System :: OS Independent
Classifier: Programming Language :: Python :: 3
Classifier: Programming Language :: Python :: 3.10
Classifier: Programming Language :: Python :: 3.11
Classifier: Programming Language :: Python :: 3.12
Classifier: Topic :: Scientific/Engineering :: Artificial Intelligence
Classifier: Topic :: Scientific/Engineering :: Image Processing
Requires-Python: <3.13,>=3.10
License-File: LICENSE.txt
Requires-Dist: neurovc[landmark]>=0.1.1a2
Requires-Dist: torch>=2.4.0
Requires-Dist: torchvision>=0.19.0
Requires-Dist: timm
Requires-Dist: gdown>=5.2.0
Requires-Dist: requests>=2.32.0
Requires-Dist: tqdm>=4.0.0
Provides-Extra: dev
Requires-Dist: pytest>=8.0.0; extra == "dev"
Requires-Dist: pytest-cov>=5.0.0; extra == "dev"
Dynamic: license-file
